{
	"categories": [
		{
			"id": 0,
			"name": "넙치",
			"superclass": "척삭동물문",
			"class": "조기어강",
			"order": "가자미목",
			"family": "넙치과",
			"supercategory": "어류"
		}
	],
	"images": [
		{
			"id": 31142,
			"file_name": "F01_U01_O0088_D2022-07-04_L420_W0749_S3_R08_B03_I00000011",
			"width": 5152,
			"height": 3864,
			"date_captured": "2022-07-04",
			"type": "RGB",
			"angle": 8
		}
	],
	"growth_levels": [
		{
			"level_id": 1,
			"level_name": "치어"
		},
		{
			"level_id": 2,
			"level_name": "준성어"
		},
		{
			"level_id": 3,
			"level_name": "성어"
		}
	],
	"annotations": [
		{
			"id": 90809,
			"fishno": 88,
			"image_id": 31142,
			"category_id": 0,
			"tanknum": 1,
			"bbox": [
				3203.8999999999996,
				1060.4533333333331,
				3504.433333333333,
				1281.56
			],
			"symptom_type": 3,
			"symptom": 10,
			"disease": [
				11
			],
			"body_weight": 749,
			"body_length": 420,
			"growth_level": 3
		},
		{
			"id": 90810,
			"fishno": 88,
			"image_id": 31142,
			"category_id": 0,
			"tanknum": 1,
			"bbox": [
				1997.4733333333331,
				2345.233333333333,
				2589.953333333333,
				2584.5866666666666
			],
			"symptom_type": 3,
			"symptom": 3,
			"disease": [
				11
			],
			"body_weight": 749,
			"body_length": 420,
			"growth_level": 3
		}
	]
}